gtest_vendor/_dummy.cpython-314t-x86_64-linux-gnu.so
ros_gtest_vendor-1.15.1.data/data/share/gtest_vendor/package.xml
ros_gtest_vendor-1.15.1.data/data/share/gtest_vendor/cmake/gtest_vendorConfig.cmake
ros_gtest_vendor-1.15.1.data/data/src/gtest_vendor/CMakeLists.txt
ros_gtest_vendor-1.15.1.data/data/src/gtest_vendor/include/gtest/gtest-assertion-result.h
ros_gtest_vendor-1.15.1.data/data/src/gtest_vendor/include/gtest/gtest-death-test.h
ros_gtest_vendor-1.15.1.data/data/src/gtest_vendor/include/gtest/gtest-matchers.h
ros_gtest_vendor-1.15.1.data/data/src/gtest_vendor/include/gtest/gtest-message.h
ros_gtest_vendor-1.15.1.data/data/src/gtest_vendor/include/gtest/gtest-param-test.h
ros_gtest_vendor-1.15.1.data/data/src/gtest_vendor/include/gtest/gtest-printers.h
ros_gtest_vendor-1.15.1.data/data/src/gtest_vendor/include/gtest/gtest-spi.h
ros_gtest_vendor-1.15.1.data/data/src/gtest_vendor/include/gtest/gtest-test-part.h
ros_gtest_vendor-1.15.1.data/data/src/gtest_vendor/include/gtest/gtest-typed-test.h
ros_gtest_vendor-1.15.1.data/data/src/gtest_vendor/include/gtest/gtest.h
ros_gtest_vendor-1.15.1.data/data/src/gtest_vendor/include/gtest/gtest_pred_impl.h
ros_gtest_vendor-1.15.1.data/data/src/gtest_vendor/include/gtest/gtest_prod.h
ros_gtest_vendor-1.15.1.data/data/src/gtest_vendor/include/gtest/internal/gtest-death-test-internal.h
ros_gtest_vendor-1.15.1.data/data/src/gtest_vendor/include/gtest/internal/gtest-filepath.h
ros_gtest_vendor-1.15.1.data/data/src/gtest_vendor/include/gtest/internal/gtest-internal.h
ros_gtest_vendor-1.15.1.data/data/src/gtest_vendor/include/gtest/internal/gtest-param-util.h
ros_gtest_vendor-1.15.1.data/data/src/gtest_vendor/include/gtest/internal/gtest-port-arch.h
ros_gtest_vendor-1.15.1.data/data/src/gtest_vendor/include/gtest/internal/gtest-port.h
ros_gtest_vendor-1.15.1.data/data/src/gtest_vendor/include/gtest/internal/gtest-string.h
ros_gtest_vendor-1.15.1.dist-info/METADATA
ros_gtest_vendor-1.15.1.dist-info/WHEEL
ros_gtest_vendor-1.15.1.dist-info/top_level.txt
ros_gtest_vendor-1.15.1.dist-info/RECORD
