Metadata-Version: 2.4
Name: ros-gtest-vendor
Version: 1.15.1
Summary: ROS package providing the GoogleTest C++ unit testing framework.
Dynamic: description
Dynamic: description-content-type
Dynamic: summary
